epic_py/__init__.py
epic_py/domain/__init__.py
epic_py/domain/pid.py
epic_py/epic_api.py
epic_py-0.1.2.dist-info/METADATA
epic_py-0.1.2.dist-info/WHEEL
epic_py-0.1.2.dist-info/RECORD
