Metadata-Version: 2.1
Name: epic-py
Version: 0.1.2
Summary: ePIC API in Python
Home-page: https://gitlab.gwdg.de/epic/epic-python-library
License: Apache-2.0
Keywords: pid,handle,persistent-identifier,epic
Author: Triet Doan
Author-email: triet.doan@gwdg.de
Requires-Python: >=3.11,<4.0
Classifier: Development Status :: 4 - Beta
Classifier: Intended Audience :: Science/Research
Classifier: License :: OSI Approved :: Apache Software License
Classifier: Natural Language :: English
Classifier: Programming Language :: Python :: 3
Classifier: Programming Language :: Python :: 3.11
Classifier: Programming Language :: Python :: 3.12
Classifier: Topic :: Software Development :: Libraries :: Python Modules
Requires-Dist: pydantic (>=2.8.2,<3.0.0)
Requires-Dist: requests (>=2.32.3,<3.0.0)
Project-URL: Repository, https://gitlab.gwdg.de/epic/epic-python-library
